[
    {
        "developer": "anonymous",
        "number": 0
    },
    {
        "developer": "azaozz",
        "number": 1
    },
    {
        "developer": "dd32",
        "number": 2
    },
    {
        "developer": "markjaquith",
        "number": 3
    },
    {
        "developer": "matt",
        "number": 4
    },
    {
        "developer": "nacin",
        "number": 5
    },
    {
        "developer": "ryan",
        "number": 6
    },
    {
        "developer": "westi",
        "number": 7
    },
    {
        "developer": "mikelittle",
        "number": 8
    },
    {
        "developer": "nbachiyski",
        "number": 9
    },
    {
        "developer": "rboren",
        "number": 10
    },
    {
        "developer": "saxmatt",
        "number": 11
    },
    {
        "developer": "wpmuguru",
        "number": 12
    },
    {
        "developer": "iandstewart",
        "number": 13
    },
    {
        "developer": "lancewillett",
        "number": 14
    },
    {
        "developer": "duck_",
        "number": 15
    },
    {
        "developer": "koopersmith",
        "number": 16
    },
    {
        "developer": "scribu",
        "number": 17
    },
    {
        "developer": "emc3",
        "number": 18
    },
    {
        "developer": "jverber",
        "number": 19
    },
    {
        "developer": "rob1n",
        "number": 20
    },
    {
        "developer": "michelvaldrighi",
        "number": 21
    },
    {
        "developer": "iammattthomas",
        "number": 22
    },
    {
        "developer": "alex_t_king",
        "number": 23
    },
    {
        "developer": "donncha",
        "number": 24
    },
    {
        "developer": "SergeyBiryukov",
        "number": 25
    },
    {
        "developer": "PeteMall",
        "number": 26
    },
    {
        "developer": "bumpbot",
        "number": 27
    },
    {
        "developer": "helen",
        "number": 28
    },
    {
        "developer": "uid26904",
        "number": 29
    },
    {
        "developer": "josephscott",
        "number": 30
    },
    {
        "developer": "dougal",
        "number": 31
    },
    {
        "developer": "potbot",
        "number": 32
    }
]