[
    {
        "developer1": "daniel",
        "developer2": "jonas",
        "count": 1
    },
    {
        "developer1": "jonas",
        "developer2": "utopiste",
        "count": 2
    },
    {
        "developer1": "cboos",
        "developer2": "daniel",
        "count": 1
    },
    {
        "developer1": "cmlenz",
        "developer2": "daniel",
        "count": 5
    },
    {
        "developer1": "cboos",
        "developer2": "jonas",
        "count": 1
    },
    {
        "developer1": "daniel",
        "developer2": "rblank",
        "count": 1
    },
    {
        "developer1": "cboos",
        "developer2": "cmlenz",
        "count": 1
    }
]